src/__init__.py
src/dcsv.py
src/dkeras.py
src/dplot.py
src/dwong.py
dwong-0.2.dist-info/LICENSE
dwong-0.2.dist-info/METADATA
dwong-0.2.dist-info/WHEEL
dwong-0.2.dist-info/top_level.txt
dwong-0.2.dist-info/RECORD
