Metadata-Version: 2.1
Name: dwong
Version: 0.2
Summary: Dowling's integrated data analysis for DQ experiemnt setup. Include data analysis functions, csv saving tools, Particle ID model, DNN model frame for ID training and EMCal ploting tools
Home-page: https://github.com/Dowling7/dwong
Author: Dowling Wong
Author-email: dowlingwong@brandeis.edu
License: MIT
Classifier: Programming Language :: Python :: 3
Classifier: License :: OSI Approved :: MIT License
Classifier: Operating System :: Unix
Classifier: Operating System :: MacOS :: MacOS X
Classifier: Operating System :: Microsoft :: Windows
Requires-Python: >=3.6
License-File: LICENSE
Requires-Dist: numpy (>=1.18.0)
Requires-Dist: keras (==2.13.1)
Requires-Dist: uproot (>=5.0.7)
Requires-Dist: sklearn (>=1.2.2)
Requires-Dist: matplotlib (>=3.7.1)
